vidlytics/__init__.py
vidlytics/main.py
vidlytics/prompts.py
vidlytics-2025.12.21192354.dist-info/METADATA
vidlytics-2025.12.21192354.dist-info/WHEEL
vidlytics-2025.12.21192354.dist-info/top_level.txt
vidlytics-2025.12.21192354.dist-info/RECORD
