Metadata-Version: 2.4
Name: vidlytics
Version: 2025.12.21192354
Summary: vidlytics extracts text from multimedia, generates domain-specific summaries & insights from prompts, enabling quick understanding without direct video processing.
Author-email: vidlytics <hi@eugene.plus>
License: MIT
Project-URL: Homepage, https://github.com/chigwell/vidlytics
Requires-Python: >=3.9
Requires-Dist: langchain-llm7>=0.0.0
Requires-Dist: llmatch-messages>=0.0.0
Requires-Dist: langchain-core>=0.3.0
